peyecoder/__init__.py
peyecoder/audio_player.py
peyecoder/av_utils.py
peyecoder/dialogs.py
peyecoder/export.py
peyecoder/file_utils.py
peyecoder/gui.py
peyecoder/models.py
peyecoder/panels.py
peyecoder/reliability.py
peyecoder/video_reader.py
peyecoder-1.2.0.dist-info/LICENSE
peyecoder-1.2.0.dist-info/METADATA
peyecoder-1.2.0.dist-info/WHEEL
peyecoder-1.2.0.dist-info/entry_points.txt
peyecoder-1.2.0.dist-info/top_level.txt
peyecoder-1.2.0.dist-info/RECORD
