Metadata-Version: 2.1
Name: peyecoder
Version: 1.2.0
Summary: Software for coding eye movements
Home-page: https://github.com/rholson1/peyecoder
Author: Rob Olson
Author-email: rolson@waisman.wisc.edu
License: UNKNOWN
Platform: UNKNOWN
Classifier: Development Status :: 4 - Beta
Classifier: Intended Audience :: Science/Research
Classifier: Programming Language :: Python :: 3
Classifier: License :: OSI Approved :: MIT License
Classifier: Operating System :: OS Independent
Requires-Python: >=3.7
Requires-Dist: numpy
Requires-Dist: opencv-python-headless
Requires-Dist: PyAudio
Requires-Dist: PySide2
Requires-Dist: python-dateutil
Requires-Dist: sortedcontainers
Requires-Dist: timecode
